pySldWrap/__init__.py
pySldWrap/sw_tools.py
pySldWrap-0.2.dist-info/LICENSE
pySldWrap-0.2.dist-info/METADATA
pySldWrap-0.2.dist-info/WHEEL
pySldWrap-0.2.dist-info/top_level.txt
pySldWrap-0.2.dist-info/RECORD
