Metadata-Version: 2.1
Name: pySldWrap
Version: 0.2
Summary: Python Solidworks interface
Home-page: https://github.com/ThomasNeve/pySldWrap
Author: Thomas Neve
Author-email: thomas.neve@ugent.be
License: MIT
Download-URL: https://github.com/ThomasNeve/pySldWrap/archive/v0.1.tar.gz
Keywords: solidworks,wrapper
Platform: UNKNOWN
Classifier: License :: OSI Approved :: MIT License
Classifier: Programming Language :: Python :: 3.5
Classifier: Programming Language :: Python :: 3.6
Classifier: Programming Language :: Python :: 3.7
Requires-Python: >=3.6
Requires-Dist: numpy
Requires-Dist: pywin32
Requires-Dist: pathlib
